test_module/__init__.py
test_module/bar.py
test_module/foo.py
myyrakle_test_module-0.4.0.dist-info/LICENSE
myyrakle_test_module-0.4.0.dist-info/METADATA
myyrakle_test_module-0.4.0.dist-info/WHEEL
myyrakle_test_module-0.4.0.dist-info/top_level.txt
myyrakle_test_module-0.4.0.dist-info/RECORD
