Metadata-Version: 2.1
Name: myyrakle-test-module
Version: 0.4.0
Summary: test module
Home-page: https://github.com/myyrakle/python_module_template
Author: myyrakle
Author-email: sssang97@naver.com
License: MIT
Classifier: Programming Language :: Python :: 3
Classifier: License :: OSI Approved :: MIT License
Classifier: Operating System :: OS Independent
License-File: LICENSE
